AUTHORS.rst
CONTRIBUTING.rst
HISTORY.rst
LICENSE
MANIFEST.in
README.rst
setup.cfg
setup.py
docs/Makefile
docs/authors.rst
docs/conf.py
docs/contributing.rst
docs/history.rst
docs/index.rst
docs/installation.rst
docs/make.bat
docs/readme.rst
docs/usage.rst
tests/__init__.py
tests/test_adapt.py
tests/test_traverse_invoke.py
traverse_invoke/__init__.py
traverse_invoke/cli.py
traverse_invoke/core.py
traverse_invoke/leaves.py
traverse_invoke.egg-info/PKG-INFO
traverse_invoke.egg-info/SOURCES.txt
traverse_invoke.egg-info/dependency_links.txt
traverse_invoke.egg-info/entry_points.txt
traverse_invoke.egg-info/not-zip-safe
traverse_invoke.egg-info/requires.txt
traverse_invoke.egg-info/top_level.txt
traverse_invoke/readers/__init__.py
traverse_invoke/readers/config.py
traverse_invoke/readers/test_config.py