Metadata-Version: 1.2
Name: traverse-invoke
Version: 0.1.1
Summary: A nested method computation model for nested data
Home-page: https://github.com/DaniloZZZ/traverse_invoke
Author: Dan Lykov
Author-email: lkvdan@gmail.com
License: MIT license
Keywords: traverse_invoke
Platform: UNKNOWN
Classifier: Development Status :: 2 - Pre-Alpha
Classifier: Intended Audience :: Developers
Classifier: License :: OSI Approved :: MIT License
Classifier: Natural Language :: English
Classifier: Programming Language :: Python :: 3
Classifier: Programming Language :: Python :: 3.5
Classifier: Programming Language :: Python :: 3.6
Classifier: Programming Language :: Python :: 3.7
Classifier: Programming Language :: Python :: 3.8
Requires-Python: >=3.5
